rgpd_gen/__init__.py
rgpd_gen/encrypt.py
rgpd_gen/randomize.py
rgpd_password-1.0.dist-info/METADATA
rgpd_password-1.0.dist-info/WHEEL
rgpd_password-1.0.dist-info/entry_points.txt
rgpd_password-1.0.dist-info/top_level.txt
rgpd_password-1.0.dist-info/RECORD
