Metadata-Version: 2.1
Name: rgpd-password
Version: 1.0
Summary: Tools to generate RGPD friendly password
Home-page: UNKNOWN
Author: Arthur RICHARD
Author-email: UNKNOWN
License: MIT
Platform: UNKNOWN
